recomp/hdb/__init__.py
recomp/hdb/provx.py
recomp_hdb_provx-0.1.1.dist-info/LICENSE.md
recomp_hdb_provx-0.1.1.dist-info/METADATA
recomp_hdb_provx-0.1.1.dist-info/WHEEL
recomp_hdb_provx-0.1.1.dist-info/top_level.txt
recomp_hdb_provx-0.1.1.dist-info/zip-safe
recomp_hdb_provx-0.1.1.dist-info/RECORD
