Metadata-Version: 2.1
Name: recomp-hdb-provx
Version: 0.1.1
Summary: A client library to access ReComp HDB service.
Home-page: http://www.recomp.org.uk
Author: Jacek Cała
Author-email: Jacek.Cala@ncl.ac.uk
License: GPLv3
Platform: UNKNOWN
Classifier: Development Status :: 3 - Alpha
Classifier: Programming Language :: Python
Classifier: Programming Language :: Python :: 3
Classifier: Programming Language :: Python :: 3.6
Classifier: Programming Language :: Python :: Implementation :: CPython
Classifier: Programming Language :: Python :: Implementation :: PyPy
Classifier: License :: OSI Approved :: GNU General Public License v3 (GPLv3)
Requires-Python: >=3.6.0
Requires-Dist: requests
